{"settings":{"wordCountPerPage":100},"categories":["category1","category2","article","category of anything","compound words","whatever"],"words":[{"word":"Word Example","meanings":["Meaning Example","You may enter BASE MEANING","and SECONDARY MEANINGS","no restriction of meanings count"],"wordId":"tpvNElXo7","wordColor":"rgb(0, 0, 0)","date":1548967353706,"categories":[{"category":"category1","value":"In categories you may record whatever you want, related to the word"},{"category":"category2","value":"any number of categories"}],"marked":false},{"word":"Color Example","meanings":["Words may be colored"],"wordId":"S93N-yq5I","wordColor":"rgb(123, 255, 97)","date":1550005036117,"categories":[],"marked":false},{"word":"Category Example","meanings":["An unlimited number","of categories","may be added"],"wordId":"SVpDZ0V8q","wordColor":"rgb(0, 0, 0)","date":1550005447855,"categories":[{"category":"article","value":"der, die or das, or plural, or...."},{"category":"category of anything","value":"...noun, verb or adjective, or"},{"category":"compound words","value":"...difficult, compound words ..."},{"category":"whatever","value":"....or whatever user finds relevant to the word..."}],"marked":false}],"dbNameId":"WorderDB.json","examQuestionsCount":20}